<?xml version="1.0" encoding="utf-8"?>
<search>
  
  
  
  <entry>
    <title>尝试一下</title>
    <link href="/2025/12/15/%E5%B0%9D%E8%AF%95%E4%B8%80%E4%B8%8B/"/>
    <url>/2025/12/15/%E5%B0%9D%E8%AF%95%E4%B8%80%E4%B8%8B/</url>
    
    <content type="html"><![CDATA[<h1 id="0-说明"><a href="#0-说明" class="headerlink" title="0.说明"></a>0.说明</h1><p>第一次自己建立博客，看看效果。</p>]]></content>
    
    
    <categories>
      
      <category>技术</category>
      
    </categories>
    
    
    <tags>
      
      <tag>不知道</tag>
      
    </tags>
    
  </entry>
  
  
  
  
</search>
